examples/__init__.py
examples/mymodels.py
examples/run.py
flask_autocrud/__init__.py
flask_autocrud/autocrud.py
flask_autocrud/config.py
flask_autocrud/model.py
flask_autocrud/qs2sqla.py
flask_autocrud/service.py
flask_autocrud/validators.py
flask_autocrud/version.py
flask_autocrud/examples/__init__.py
flask_autocrud/examples/mymodels.py
flask_autocrud/examples/run.py
flask_autocrud/scripts/__init__.py
flask_autocrud/scripts/default.py
flask_autocrud/scripts/gunicorn.py
flask_autocrud/scripts/run.py
flask_autocrud/scripts/waitress.py
tests/__init__.py
tests/models.py
tests/test_auto.py
tests/test_configuration.py
tests/test_custom.py
tests/test_fetch.py
tests/test_qs2sqla.py
Flask_AutoCRUD-2.1.1.dist-info/LICENSE
Flask_AutoCRUD-2.1.1.dist-info/METADATA
Flask_AutoCRUD-2.1.1.dist-info/WHEEL
Flask_AutoCRUD-2.1.1.dist-info/entry_points.txt
Flask_AutoCRUD-2.1.1.dist-info/top_level.txt
Flask_AutoCRUD-2.1.1.dist-info/RECORD
