Metadata-Version: 2.1
Name: Flask-AutoCRUD
Version: 2.1.1
Summary: Automatically generated a RESTful API services for CRUD operation and queries on database
Home-page: https://github.com/cs91chris/flask_autocrud/
Author: cs91chris
Author-email: cs91chris@voidbrain.me
License: MIT
Platform: any
Classifier: Environment :: Web Environment
Classifier: Intended Audience :: Developers
Classifier: License :: OSI Approved :: MIT License
Classifier: Operating System :: OS Independent
Classifier: Programming Language :: Python :: 3
Classifier: Topic :: Internet :: WWW/HTTP :: Dynamic Content
Classifier: Topic :: Software Development :: Libraries :: Python Modules
Requires-Dist: Flask (==1.1.*)
Requires-Dist: Flask-SQLAlchemy (==2.4.*)
Requires-Dist: Flask-ResponseBuilder (==2.*)
Requires-Dist: Flask-ErrorsHandler (==2.*)
Requires-Dist: sqlalchemy-filters (==0.10.*)
Requires-Dist: colander (==1.7.*)
Requires-Dist: PyYAML (==5.*)
